limecore/logging/__init__.py
limecore/logging/handler_factory.py
limecore/logging/logger_factory.py
limecore/logging/module.py
limecore_logging-0.2.1.dist-info/LICENSE.txt
limecore_logging-0.2.1.dist-info/METADATA
limecore_logging-0.2.1.dist-info/WHEEL
limecore_logging-0.2.1.dist-info/top_level.txt
limecore_logging-0.2.1.dist-info/RECORD
