Metadata-Version: 2.1
Name: limecore-logging
Version: 0.2.1
Summary: limecore: Logging
Home-page: https://github.com/limecore/logging
Author: Daniel Bradberry
Author-email: daniel@danielbradberry.com
License: MIT
Platform: UNKNOWN
Classifier: Programming Language :: Python :: 3
Classifier: License :: OSI Approved :: MIT License
Classifier: Operating System :: OS Independent
Requires-Python: >=3.6
Requires-Dist: injector
Requires-Dist: limecore-core-configuration (>=0.2.1)
